proxies_scraper/__init__.py
proxies_scraper/adapters/__init__.py
proxies_scraper/adapters/implementations/__init__.py
proxies_scraper/adapters/implementations/freeProxyCz.py
proxies_scraper/adapters/implementations/freeProxyList.py
proxies_scraper/adapters/implementations/geonode.py
proxies_scraper/adapters/ports/__init__.py
proxies_scraper/adapters/ports/proxies_source.py
proxies_scraper/app.py
proxies_scraper/core/__init__.py
proxies_scraper/core/proxy_scraper.py
proxies_scraper/main.py
proxies_scraper/utils/file_operation.py
proxies_scraper/utils/logger.py
proxies_scraper/utils/postman.py
proxies_scraper/utils/time_operations.py
proxies_scraper/utils/timer.py
proxies_scraper-1.0.2.dist-info/METADATA
proxies_scraper-1.0.2.dist-info/WHEEL
proxies_scraper-1.0.2.dist-info/RECORD
