Metadata-Version: 2.1
Name: proxies-scraper
Version: 1.0.2
Summary: A Python package for proxies scraping
Author: Carlosman1996
Author-email: cmmolinas01@gmail.com
Requires-Python: >=3.12,<4.0
Classifier: Programming Language :: Python :: 3
Classifier: Programming Language :: Python :: 3.12
Requires-Dist: beautifulsoup4 (>=4.12.3,<5.0.0)
Requires-Dist: flask (>=3.0.3,<4.0.0)
Requires-Dist: requests (>=2.32.3,<3.0.0)
